mpt_extension_sdk/__init__.py
mpt_extension_sdk/constants.py
mpt_extension_sdk/airtable/__init__.py
mpt_extension_sdk/airtable/wrap_http_error.py
mpt_extension_sdk/core/__init__.py
mpt_extension_sdk/core/extension.py
mpt_extension_sdk/core/security.py
mpt_extension_sdk/core/utils.py
mpt_extension_sdk/core/events/__init__.py
mpt_extension_sdk/core/events/dataclasses.py
mpt_extension_sdk/core/events/registry.py
mpt_extension_sdk/flows/__init__.py
mpt_extension_sdk/flows/context.py
mpt_extension_sdk/flows/pipeline.py
mpt_extension_sdk/key_vault/__init__.py
mpt_extension_sdk/key_vault/base.py
mpt_extension_sdk/mpt_http/__init__.py
mpt_extension_sdk/mpt_http/base.py
mpt_extension_sdk/mpt_http/mpt.py
mpt_extension_sdk/mpt_http/utils.py
mpt_extension_sdk/mpt_http/wrap_http_error.py
mpt_extension_sdk/runtime/__init__.py
mpt_extension_sdk/runtime/errors.py
mpt_extension_sdk/runtime/initializer.py
mpt_extension_sdk/runtime/logging.py
mpt_extension_sdk/runtime/master.py
mpt_extension_sdk/runtime/swoext.py
mpt_extension_sdk/runtime/tracer.py
mpt_extension_sdk/runtime/utils.py
mpt_extension_sdk/runtime/workers.py
mpt_extension_sdk/runtime/commands/__init__.py
mpt_extension_sdk/runtime/commands/django.py
mpt_extension_sdk/runtime/commands/run.py
mpt_extension_sdk/runtime/djapp/__init__.py
mpt_extension_sdk/runtime/djapp/apps.py
mpt_extension_sdk/runtime/djapp/middleware.py
mpt_extension_sdk/runtime/djapp/conf/__init__.py
mpt_extension_sdk/runtime/djapp/conf/default.py
mpt_extension_sdk/runtime/djapp/conf/urls.py
mpt_extension_sdk/runtime/djapp/management/__init__.py
mpt_extension_sdk/runtime/djapp/management/commands/__init__.py
mpt_extension_sdk/runtime/djapp/management/commands/consume_events.py
mpt_extension_sdk/runtime/events/__init__.py
mpt_extension_sdk/runtime/events/dispatcher.py
mpt_extension_sdk/runtime/events/producers.py
mpt_extension_sdk/runtime/events/utils.py
mpt_extension_sdk/swo_rql/__init__.py
mpt_extension_sdk/swo_rql/constants.py
mpt_extension_sdk-5.17.2.dist-info/METADATA
mpt_extension_sdk-5.17.2.dist-info/WHEEL
mpt_extension_sdk-5.17.2.dist-info/entry_points.txt
mpt_extension_sdk-5.17.2.dist-info/licenses/LICENSE
mpt_extension_sdk-5.17.2.dist-info/RECORD
