Metadata-Version: 2.4
Name: mpt-extension-sdk
Version: 5.17.2
Summary: Extensions SDK for SoftwareONE Marketplace Platform
Author: SoftwareOne AG
License: Apache-2.0 license
License-File: LICENSE
Requires-Python: <4,>=3.12
Requires-Dist: azure-identity==1.25.*
Requires-Dist: azure-keyvault-secrets==4.10.*
Requires-Dist: azure-monitor-opentelemetry-exporter==1.0.0b25
Requires-Dist: click==8.3.*
Requires-Dist: debugpy==1.8.*
Requires-Dist: django-ninja==1.1.*
Requires-Dist: django==4.2.*
Requires-Dist: gunicorn==23.0.*
Requires-Dist: jinja2==3.1.*
Requires-Dist: markdown-it-py==4.0.*
Requires-Dist: openpyxl==3.1.*
Requires-Dist: opentelemetry-api==1.30.*
Requires-Dist: opentelemetry-instrumentation-django==0.51b0
Requires-Dist: opentelemetry-instrumentation-logging==0.51b0
Requires-Dist: opentelemetry-instrumentation-requests==0.51b0
Requires-Dist: opentelemetry-sdk==1.30.*
Requires-Dist: phonenumbers==9.0.*
Requires-Dist: pyairtable==3.3.*
Requires-Dist: pyfiglet==1.0.*
Requires-Dist: pyjwt==2.10.*
Requires-Dist: pymsteams==0.2.*
Requires-Dist: regex==2024.11.*
Requires-Dist: requests==2.32.*
Requires-Dist: rich==14.2.*
Requires-Dist: types-openpyxl==3.1.*
Requires-Dist: typing-extensions==4.15.*
Requires-Dist: watchfiles==1.1.*
